gamba/__init__.py
gamba/_nbdev.py
gamba/about.py
gamba/advanced.py
gamba/beginner.py
gamba/bravenman2010.py
gamba/data.py
gamba/intermediate.py
gamba/labelling.py
gamba/labrie2007.py
gamba/labrie2008.py
gamba/laplante2009.py
gamba/machine_learning.py
gamba/measures.py
gamba/philander2014.py
gamba/replications.py
gamba/statistics.py
gamba-0.1.4.dist-info/LICENSE
gamba-0.1.4.dist-info/METADATA
gamba-0.1.4.dist-info/WHEEL
gamba-0.1.4.dist-info/entry_points.txt
gamba-0.1.4.dist-info/top_level.txt
gamba-0.1.4.dist-info/RECORD
