Metadata-Version: 2.1
Name: gamba
Version: 0.1.4
Summary: Gambling Transaction Analysis in Python
Home-page: https://github.com/gamba-dev/gamba/tree/main/
Author: Oliver J. Scholten
Author-email: oliver@gamba.dev
License: Apache Software License 2.0
Keywords: gambing python transaction analysis
Platform: UNKNOWN
Classifier: Development Status :: 3 - Alpha
Classifier: Intended Audience :: Developers
Classifier: License :: OSI Approved :: Apache Software License
Classifier: Natural Language :: English
Classifier: Programming Language :: Python :: 3.6
Classifier: Programming Language :: Python :: 3.7
Classifier: Programming Language :: Python :: 3.8
Requires-Python: >=3.6
License-File: LICENSE
Requires-Dist: matplotlib (>=3.3.1)
Requires-Dist: pandas (>=1.0.5)
Requires-Dist: scikit-learn (>=0.23.2)
Requires-Dist: pysan (>=0.2.1)
